{
  "required": true,
  "minVersion": "0.8",
  "package": "com.github.thedeathlycow.lostinthecold.mixins",
  "compatibilityLevel": "JAVA_17",
  "mixins": [
    "entity.EntityMixin",
    "entity.LivingEntityMixin",
    "entity.PlayerEntityMixin",
    "entity.mob.PiglinBrainMixin",
    "item.ArmorItemMixin",
    "server.ServerWorldMixin",
    "world.biome.BiomeMixin",
    "world.gen.feature.FreezeTopLayerMixin"
  ],
  "client": [
    "client.gui.InGameHudInvoker",
    "client.gui.InGameHudMixin"
  ],
  "injectors": {
    "defaultRequire": 1
  }
}
